odoo/addons/easy_my_coop_initial_import/README.rst
odoo/addons/easy_my_coop_initial_import/__init__.py
odoo/addons/easy_my_coop_initial_import/__manifest__.py
odoo/addons/easy_my_coop_initial_import/models/__init__.py
odoo/addons/easy_my_coop_initial_import/models/subscription_request.py
odoo/addons/easy_my_coop_initial_import/readme/CONTRIBUTORS.rst
odoo/addons/easy_my_coop_initial_import/readme/DESCRIPTION.rst
odoo/addons/easy_my_coop_initial_import/readme/INSTALL.rst
odoo/addons/easy_my_coop_initial_import/readme/ROADMAP.rst
odoo/addons/easy_my_coop_initial_import/readme/USAGE.rst
odoo/addons/easy_my_coop_initial_import/security/res_groups.xml
odoo/addons/easy_my_coop_initial_import/static/description/index.html
odoo/addons/easy_my_coop_initial_import/wizards/__init__.py
odoo/addons/easy_my_coop_initial_import/wizards/pay_capital_release_invoices/__init__.py
odoo/addons/easy_my_coop_initial_import/wizards/pay_capital_release_invoices/pay_capital_release_invoices.py
odoo/addons/easy_my_coop_initial_import/wizards/pay_capital_release_invoices/pay_capital_release_invoices.xml
odoo/addons/easy_my_coop_initial_import/wizards/validate_subscription_requests/__init__.py
odoo/addons/easy_my_coop_initial_import/wizards/validate_subscription_requests/validate_subscription_requests.py
odoo/addons/easy_my_coop_initial_import/wizards/validate_subscription_requests/validate_subscription_requests.xml
odoo12_addon_easy_my_coop_initial_import-12.0.1.0.0.99.dev6.dist-info/METADATA
odoo12_addon_easy_my_coop_initial_import-12.0.1.0.0.99.dev6.dist-info/WHEEL
odoo12_addon_easy_my_coop_initial_import-12.0.1.0.0.99.dev6.dist-info/top_level.txt
odoo12_addon_easy_my_coop_initial_import-12.0.1.0.0.99.dev6.dist-info/RECORD
