Metadata-Version: 2.1
Name: odoo12-addon-easy-my-coop-initial-import
Version: 12.0.1.0.0.99.dev6
Summary: Facilitate import cooperators data from another module/ERP to EMC.
Home-page: https://coopdevs.org
Author: Coopdevs Treball SCCL
License: AGPL-3
Platform: UNKNOWN
Classifier: Programming Language :: Python
Classifier: Framework :: Odoo
Classifier: Framework :: Odoo :: 12.0
Classifier: License :: OSI Approved :: GNU Affero General Public License v3
Requires-Python: >=3.5
Requires-Dist: odoo12-addon-easy-my-coop
Requires-Dist: odoo12-addon-queue-job
Requires-Dist: odoo (<12.1dev,>=12.0a)
